eagle_lang/__init__.py
eagle_lang/cli.py
eagle_lang/config.py
eagle_lang/init.py
eagle_lang/interpreter.py
eagle_lang/providers.py
eagle_lang/default_config/eagle_config.json
eagle_lang/default_config/eagle_rules.md
eagle_lang/default_config/tools/ask_permission/README.md
eagle_lang/default_config/tools/ask_permission/__init__.py
eagle_lang/default_config/tools/ask_permission/tests.py
eagle_lang/default_config/tools/call_eagle/__init__.py
eagle_lang/default_config/tools/git/__init__.py
eagle_lang/default_config/tools/make_rule/README.md
eagle_lang/default_config/tools/make_rule/__init__.py
eagle_lang/default_config/tools/make_rule/tests.py
eagle_lang/default_config/tools/make_tool/__init__.py
eagle_lang/default_config/tools/print/README.md
eagle_lang/default_config/tools/print/__init__.py
eagle_lang/default_config/tools/print/tests.py
eagle_lang/default_config/tools/read/README.md
eagle_lang/default_config/tools/read/__init__.py
eagle_lang/default_config/tools/read/tests.py
eagle_lang/default_config/tools/search/__init__.py
eagle_lang/default_config/tools/shell/__init__.py
eagle_lang/default_config/tools/web/__init__.py
eagle_lang/default_config/tools/write/README.md
eagle_lang/default_config/tools/write/__init__.py
eagle_lang/default_config/tools/write/tests.py
eagle_lang/tools/__init__.py
eagle_lang/tools/base.py
eagle_lang-0.1.1.dist-info/licenses/LICENSE
eagle_lang-0.1.1.dist-info/METADATA
eagle_lang-0.1.1.dist-info/WHEEL
eagle_lang-0.1.1.dist-info/entry_points.txt
eagle_lang-0.1.1.dist-info/top_level.txt
eagle_lang-0.1.1.dist-info/RECORD
